breathrate/Plot.py
breathrate/__init__.py
breathrate/breathrate.py
breathrate/test.py
breathrate-0.1.1.dist-info/LICENSE
breathrate-0.1.1.dist-info/METADATA
breathrate-0.1.1.dist-info/WHEEL
breathrate-0.1.1.dist-info/top_level.txt
breathrate-0.1.1.dist-info/RECORD
